dxlstreamingclient/__init__.py
dxlstreamingclient/_compat.py
dxlstreamingclient/_version.py
dxlstreamingclient/auth.py
dxlstreamingclient/channel.py
dxlstreamingclient/error.py
dxlstreamingclient/_config/__init__.py
dxlstreamingclient/_config/sample/__init__.py
dxlstreamingclient-0.1.2.dist-info/LICENSE
dxlstreamingclient-0.1.2.dist-info/METADATA
dxlstreamingclient-0.1.2.dist-info/WHEEL
dxlstreamingclient-0.1.2.dist-info/top_level.txt
dxlstreamingclient-0.1.2.dist-info/RECORD
