Metadata-Version: 2.1
Name: dxlstreamingclient
Version: 0.1.2
Summary: OpenDXL Streaming client library
Home-page: http://www.mcafee.com
Author: McAfee LLC
License: Apache License 2.0
Keywords: opendxl,dxl,mcafee,client,streaming
Platform: UNKNOWN
Classifier: Development Status :: 4 - Beta
Classifier: Topic :: Software Development :: Libraries :: Python Modules
Classifier: License :: OSI Approved :: Apache Software License
Classifier: Programming Language :: Python
Classifier: Programming Language :: Python :: 2
Classifier: Programming Language :: Python :: 2.7
Classifier: Programming Language :: Python :: 3
Classifier: Programming Language :: Python :: 3.4
Classifier: Programming Language :: Python :: 3.5
Classifier: Programming Language :: Python :: 3.6
Classifier: Programming Language :: Python :: 3.7
Requires-Python: >=2.7.9,!=3.0.*,!=3.1.*,!=3.2.*,!=3.3.*
Requires-Dist: furl
Requires-Dist: requests
Requires-Dist: retrying
Provides-Extra: test
Requires-Dist: nose ; extra == 'test'
Requires-Dist: mock ; extra == 'test'
Requires-Dist: astroid (<2.3.0) ; extra == 'test'
Requires-Dist: pylint (<=2.3.1) ; extra == 'test'
